CHANGES.rst
LICENSE
MANIFEST.in
README.rst
ez_setup.py
setup.py
django_logdb.egg-info/PKG-INFO
django_logdb.egg-info/SOURCES.txt
django_logdb.egg-info/dependency_links.txt
django_logdb.egg-info/not-zip-safe
django_logdb.egg-info/top_level.txt
djangologdb/__init__.py
djangologdb/admin.py
djangologdb/handlers.py
djangologdb/middleware.py
djangologdb/models.py
djangologdb/settings.py
djangologdb/tests.py
djangologdb/urls.py
djangologdb/utils.py
djangologdb/views.py
djangologdb/management/__init__.py
djangologdb/management/commands/__init__.py
djangologdb/management/commands/aggregate_logs.py
djangologdb/media/js/excanvas.min.js
djangologdb/media/js/jquery-1.3.2.min.js
djangologdb/media/js/jquery.flot-0.6.min.js
djangologdb/templates/admin/djangologdb/change_list.html
djangologdb/templates/admin/djangologdb/djangologdb_change_list.html
djangologdb/templates/admin/djangologdb/logaggregate/change_form.html
djangologdb/templates/admin/djangologdb/logaggregate/djangologdb_change_form.html
djangologdb/templates/admin/djangologdb/logentry/change_form.html
djangologdb/templates/admin/djangologdb/logentry/djangologdb_change_form.html
djangologdb/templatetags/__init__.py
djangologdb/templatetags/djangologdb_tags.py
testproject/__init__.py
testproject/manage.py
testproject/settings.py
testproject/urls.py
testproject/views.py
testproject/templates/index.html