Metadata-Version: 1.0
Name: django-logdb
Version: 1.0
Summary: Django-logdb enables you to log entries to a database and aggregate them periodically.
Home-page: http://github.com/joeribekker/django-logdb
Author: Joeri Bekker
Author-email: joeri@maykinmedia.nl
License: MIT
Platform: any
Classifier: Development Status :: 4 - Beta
Classifier: Framework :: Django
Classifier: Intended Audience :: Developers
Classifier: Intended Audience :: System Administrators
Classifier: License :: OSI Approved :: BSD License
Classifier: Operating System :: OS Independent
Classifier: Programming Language :: Python
Classifier: Topic :: Software Development
